{
    "date": "20220106",
    "visiting_team": "GSW",
    "home_team": "NOP",
    "home_team_score": 101,
    "visiting_team_score": 96,
    "box_score": {
        "poolejo01": {
            "mp": 32.57,
            "home": 0,
            "fg": 3.0,
            "fga": 14.0,
            "fg_pct": 0.214,
            "fg3": 2.0,
            "fg3a": 9.0,
            "fg3_pct": 0.222,
            "ft": 3.0,
            "fta": 3.0,
            "ft_pct": 1.0,
            "orb": 0.0,
            "drb": 0.0,
            "trb": 0.0,
            "ast": 5.0,
            "stl": 3.0,
            "blk": 0.0,
            "tov": 3.0,
            "pf": 5.0,
            "pts": 11.0,
            "plus_minus": -1.0,
            "ts_pct": 0.359,
            "efg_pct": 0.286,
            "fg3a_per_fga_pct": 0.643,
            "fta_per_fga_pct": 0.214,
            "orb_pct": 0.0,
            "drb_pct": 0.0,
            "trb_pct": 0.0,
            "ast_pct": 22.6,
            "stl_pct": 4.4,
            "blk_pct": 0.0,
            "tov_pct": 16.4,
            "usg_pct": 24.8,
            "off_rtg": 73.0,
            "def_rtg": 101.0,
            "bpm": -6.0
        },
        "wiggian01": {
            "mp": 31.93,
            "home": 0,
            "fg": 7.0,
            "fga": 17.0,
            "fg_pct": 0.412,
            "fg3": 1.0,
            "fg3a": 6.0,
            "fg3_pct": 0.167,
            "ft": 6.0,
            "fta": 7.0,
            "ft_pct": 0.857,
            "orb": 0.0,
            "drb": 4.0,
            "trb": 4.0,
            "ast": 1.0,
            "stl": 2.0,
            "blk": 1.0,
            "tov": 2.0,
            "pf": 3.0,
            "pts": 21.0,
            "plus_minus": -8.0,
            "ts_pct": 0.523,
            "efg_pct": 0.441,
            "fg3a_per_fga_pct": 0.353,
            "fta_per_fga_pct": 0.412,
            "orb_pct": 0.0,
            "drb_pct": 14.0,
            "trb_pct": 6.8,
            "ast_pct": 5.7,
            "stl_pct": 3.0,
            "blk_pct": 3.1,
            "tov_pct": 9.1,
            "usg_pct": 30.5,
            "off_rtg": 98.0,
            "def_rtg": 99.0,
            "bpm": 0.5
        },
        "porteot01": {
            "mp": 23.97,
            "home": 0,
            "fg": 2.0,
            "fga": 6.0,
            "fg_pct": 0.333,
            "fg3": 1.0,
            "fg3a": 3.0,
            "fg3_pct": 0.333,
            "ft": 0.0,
            "fta": 0.0,
            "ft_pct": 0,
            "orb": 0.0,
            "drb": 7.0,
            "trb": 7.0,
            "ast": 0.0,
            "stl": 0.0,
            "blk": 0.0,
            "tov": 1.0,
            "pf": 2.0,
            "pts": 5.0,
            "plus_minus": -11.0,
            "ts_pct": 0.417,
            "efg_pct": 0.417,
            "fg3a_per_fga_pct": 0.5,
            "fta_per_fga_pct": 0.0,
            "orb_pct": 0.0,
            "drb_pct": 32.6,
            "trb_pct": 15.8,
            "ast_pct": 0.0,
            "stl_pct": 0.0,
            "blk_pct": 0.0,
            "tov_pct": 14.3,
            "usg_pct": 12.9,
            "off_rtg": 69.0,
            "def_rtg": 104.0,
            "bpm": -8.5
        },
        "looneke01": {
            "mp": 19.65,
            "home": 0,
            "fg": 3.0,
            "fga": 7.0,
            "fg_pct": 0.429,
            "fg3": 0.0,
            "fg3a": 0.0,
            "fg3_pct": 0,
            "ft": 0.0,
            "fta": 0.0,
            "ft_pct": 0,
            "orb": 3.0,
            "drb": 6.0,
            "trb": 9.0,
            "ast": 2.0,
            "stl": 1.0,
            "blk": 1.0,
            "tov": 1.0,
            "pf": 3.0,
            "pts": 6.0,
            "plus_minus": -11.0,
            "ts_pct": 0.429,
            "efg_pct": 0.429,
            "fg3a_per_fga_pct": 0.0,
            "fta_per_fga_pct": 0.0,
            "orb_pct": 15.9,
            "drb_pct": 34.1,
            "trb_pct": 24.7,
            "ast_pct": 16.5,
            "stl_pct": 2.4,
            "blk_pct": 5.0,
            "tov_pct": 12.5,
            "usg_pct": 17.9,
            "off_rtg": 98.0,
            "def_rtg": 95.0,
            "bpm": 0.3
        },
        "paytoga02": {
            "mp": 14.02,
            "home": 0,
            "fg": 2.0,
            "fga": 3.0,
            "fg_pct": 0.667,
            "fg3": 0.0,
            "fg3a": 1.0,
            "fg3_pct": 0.0,
            "ft": 0.0,
            "fta": 0.0,
            "ft_pct": 0,
            "orb": 0.0,
            "drb": 1.0,
            "trb": 1.0,
            "ast": 0.0,
            "stl": 1.0,
            "blk": 0.0,
            "tov": 1.0,
            "pf": 2.0,
            "pts": 4.0,
            "plus_minus": -11.0,
            "ts_pct": 0.667,
            "efg_pct": 0.667,
            "fg3a_per_fga_pct": 0.333,
            "fta_per_fga_pct": 0.0,
            "orb_pct": 0.0,
            "drb_pct": 8.0,
            "trb_pct": 3.8,
            "ast_pct": 0.0,
            "stl_pct": 3.4,
            "blk_pct": 0.0,
            "tov_pct": 25.0,
            "usg_pct": 12.6,
            "off_rtg": 88.0,
            "def_rtg": 102.0,
            "bpm": -5.3
        },
        "leeda03": {
            "mp": 29.62,
            "home": 0,
            "fg": 5.0,
            "fga": 10.0,
            "fg_pct": 0.5,
            "fg3": 1.0,
            "fg3a": 4.0,
            "fg3_pct": 0.25,
            "ft": 1.0,
            "fta": 2.0,
            "ft_pct": 0.5,
            "orb": 1.0,
            "drb": 4.0,
            "trb": 5.0,
            "ast": 3.0,
            "stl": 3.0,
            "blk": 1.0,
            "tov": 1.0,
            "pf": 1.0,
            "pts": 12.0,
            "plus_minus": 5.0,
            "ts_pct": 0.551,
            "efg_pct": 0.55,
            "fg3a_per_fga_pct": 0.4,
            "fta_per_fga_pct": 0.2,
            "orb_pct": 3.5,
            "drb_pct": 15.1,
            "trb_pct": 9.1,
            "ast_pct": 16.8,
            "stl_pct": 4.8,
            "blk_pct": 3.3,
            "tov_pct": 8.4,
            "usg_pct": 17.7,
            "off_rtg": 109.0,
            "def_rtg": 95.0,
            "bpm": 7.4
        },
        "moodymo01": {
            "mp": 23.07,
            "home": 0,
            "fg": 3.0,
            "fga": 6.0,
            "fg_pct": 0.5,
            "fg3": 0.0,
            "fg3a": 3.0,
            "fg3_pct": 0.0,
            "ft": 4.0,
            "fta": 4.0,
            "ft_pct": 1.0,
            "orb": 1.0,
            "drb": 4.0,
            "trb": 5.0,
            "ast": 0.0,
            "stl": 0.0,
            "blk": 0.0,
            "tov": 0.0,
            "pf": 0.0,
            "pts": 10.0,
            "plus_minus": 4.0,
            "ts_pct": 0.644,
            "efg_pct": 0.5,
            "fg3a_per_fga_pct": 0.5,
            "fta_per_fga_pct": 0.667,
            "orb_pct": 4.5,
            "drb_pct": 19.4,
            "trb_pct": 11.7,
            "ast_pct": 0.0,
            "stl_pct": 0.0,
            "blk_pct": 0.0,
            "tov_pct": 0.0,
            "usg_pct": 14.8,
            "off_rtg": 138.0,
            "def_rtg": 107.0,
            "bpm": 0.4
        },
        "iguodan01": {
            "mp": 20.28,
            "home": 0,
            "fg": 2.0,
            "fga": 3.0,
            "fg_pct": 0.667,
            "fg3": 1.0,
            "fg3a": 2.0,
            "fg3_pct": 0.5,
            "ft": 0.0,
            "fta": 0.0,
            "ft_pct": 0,
            "orb": 0.0,
            "drb": 3.0,
            "trb": 3.0,
            "ast": 7.0,
            "stl": 1.0,
            "blk": 1.0,
            "tov": 2.0,
            "pf": 3.0,
            "pts": 5.0,
            "plus_minus": 1.0,
            "ts_pct": 0.833,
            "efg_pct": 0.833,
            "fg3a_per_fga_pct": 0.667,
            "fta_per_fga_pct": 0.0,
            "orb_pct": 0.0,
            "drb_pct": 16.5,
            "trb_pct": 8.0,
            "ast_pct": 51.3,
            "stl_pct": 2.4,
            "blk_pct": 4.8,
            "tov_pct": 40.0,
            "usg_pct": 10.9,
            "off_rtg": 124.0,
            "def_rtg": 99.0,
            "bpm": 9.0
        },
        "kuminjo01": {
            "mp": 20.2,
            "home": 0,
            "fg": 6.0,
            "fga": 14.0,
            "fg_pct": 0.429,
            "fg3": 0.0,
            "fg3a": 2.0,
            "fg3_pct": 0.0,
            "ft": 1.0,
            "fta": 2.0,
            "ft_pct": 0.5,
            "orb": 3.0,
            "drb": 3.0,
            "trb": 6.0,
            "ast": 1.0,
            "stl": 0.0,
            "blk": 1.0,
            "tov": 2.0,
            "pf": 4.0,
            "pts": 13.0,
            "plus_minus": 6.0,
            "ts_pct": 0.437,
            "efg_pct": 0.429,
            "fg3a_per_fga_pct": 0.143,
            "fta_per_fga_pct": 0.143,
            "orb_pct": 15.5,
            "drb_pct": 16.6,
            "trb_pct": 16.0,
            "ast_pct": 10.4,
            "stl_pct": 0.0,
            "blk_pct": 4.8,
            "tov_pct": 11.8,
            "usg_pct": 36.8,
            "off_rtg": 85.0,
            "def_rtg": 104.0,
            "bpm": -7.1
        },
        "chiozch01": {
            "mp": 3.45,
            "home": 0,
            "fg": 0.0,
            "fga": 1.0,
            "fg_pct": 0.0,
            "fg3": 0.0,
            "fg3a": 0.0,
            "fg3_pct": 0,
            "ft": 0.0,
            "fta": 0.0,
            "ft_pct": 0,
            "orb": 0.0,
            "drb": 1.0,
            "trb": 1.0,
            "ast": 2.0,
            "stl": 0.0,
            "blk": 0.0,
            "tov": 0.0,
            "pf": 0.0,
            "pts": 0.0,
            "plus_minus": -6.0,
            "ts_pct": 0.0,
            "efg_pct": 0.0,
            "fg3a_per_fga_pct": 0.0,
            "fta_per_fga_pct": 0.0,
            "orb_pct": 0.0,
            "drb_pct": 32.4,
            "trb_pct": 15.6,
            "ast_pct": 75.2,
            "stl_pct": 0.0,
            "blk_pct": 0.0,
            "tov_pct": 0.0,
            "usg_pct": 12.8,
            "off_rtg": 77.0,
            "def_rtg": 104.0,
            "bpm": 0.4
        },
        "joneshe01": {
            "mp": 37.47,
            "home": 1,
            "fg": 4.0,
            "fga": 8.0,
            "fg_pct": 0.5,
            "fg3": 0.0,
            "fg3a": 0.0,
            "fg3_pct": 0,
            "ft": 5.0,
            "fta": 6.0,
            "ft_pct": 0.833,
            "orb": 1.0,
            "drb": 5.0,
            "trb": 6.0,
            "ast": 2.0,
            "stl": 5.0,
            "blk": 0.0,
            "tov": 0.0,
            "pf": 1.0,
            "pts": 13.0,
            "plus_minus": -4.0,
            "ts_pct": 0.611,
            "efg_pct": 0.5,
            "fg3a_per_fga_pct": 0.0,
            "fta_per_fga_pct": 0.75,
            "orb_pct": 3.0,
            "drb_pct": 13.9,
            "trb_pct": 8.6,
            "ast_pct": 8.6,
            "stl_pct": 6.4,
            "blk_pct": 0.0,
            "tov_pct": 0.0,
            "usg_pct": 12.1,
            "off_rtg": 136.0,
            "def_rtg": 87.0,
            "bpm": 9.4
        },
        "ingrabr01": {
            "mp": 34.78,
            "home": 1,
            "fg": 12.0,
            "fga": 21.0,
            "fg_pct": 0.571,
            "fg3": 1.0,
            "fg3a": 4.0,
            "fg3_pct": 0.25,
            "ft": 7.0,
            "fta": 8.0,
            "ft_pct": 0.875,
            "orb": 2.0,
            "drb": 9.0,
            "trb": 11.0,
            "ast": 6.0,
            "stl": 0.0,
            "blk": 0.0,
            "tov": 2.0,
            "pf": 2.0,
            "pts": 32.0,
            "plus_minus": -3.0,
            "ts_pct": 0.653,
            "efg_pct": 0.595,
            "fg3a_per_fga_pct": 0.19,
            "fta_per_fga_pct": 0.381,
            "orb_pct": 6.4,
            "drb_pct": 27.0,
            "trb_pct": 17.1,
            "ast_pct": 44.9,
            "stl_pct": 0.0,
            "blk_pct": 0.0,
            "tov_pct": 7.5,
            "usg_pct": 32.5,
            "off_rtg": 130.0,
            "def_rtg": 98.0,
            "bpm": 14.1
        },
        "hartjo01": {
            "mp": 34.08,
            "home": 1,
            "fg": 4.0,
            "fga": 10.0,
            "fg_pct": 0.4,
            "fg3": 1.0,
            "fg3a": 5.0,
            "fg3_pct": 0.2,
            "ft": 5.0,
            "fta": 6.0,
            "ft_pct": 0.833,
            "orb": 2.0,
            "drb": 4.0,
            "trb": 6.0,
            "ast": 2.0,
            "stl": 0.0,
            "blk": 0.0,
            "tov": 3.0,
            "pf": 5.0,
            "pts": 14.0,
            "plus_minus": -2.0,
            "ts_pct": 0.554,
            "efg_pct": 0.45,
            "fg3a_per_fga_pct": 0.5,
            "fta_per_fga_pct": 0.6,
            "orb_pct": 6.6,
            "drb_pct": 12.2,
            "trb_pct": 9.5,
            "ast_pct": 9.6,
            "stl_pct": 0.0,
            "blk_pct": 0.0,
            "tov_pct": 19.2,
            "usg_pct": 19.5,
            "off_rtg": 100.0,
            "def_rtg": 101.0,
            "bpm": -4.1
        },
        "valanjo01": {
            "mp": 31.58,
            "home": 1,
            "fg": 2.0,
            "fga": 6.0,
            "fg_pct": 0.333,
            "fg3": 0.0,
            "fg3a": 2.0,
            "fg3_pct": 0.0,
            "ft": 4.0,
            "fta": 4.0,
            "ft_pct": 1.0,
            "orb": 2.0,
            "drb": 8.0,
            "trb": 10.0,
            "ast": 4.0,
            "stl": 1.0,
            "blk": 2.0,
            "tov": 4.0,
            "pf": 3.0,
            "pts": 8.0,
            "plus_minus": 14.0,
            "ts_pct": 0.515,
            "efg_pct": 0.333,
            "fg3a_per_fga_pct": 0.333,
            "fta_per_fga_pct": 0.667,
            "orb_pct": 7.1,
            "drb_pct": 26.4,
            "trb_pct": 17.1,
            "ast_pct": 19.0,
            "stl_pct": 1.5,
            "blk_pct": 5.6,
            "tov_pct": 34.0,
            "usg_pct": 15.9,
            "off_rtg": 89.0,
            "def_rtg": 91.0,
            "bpm": 0.3
        },
        "grahade01": {
            "mp": 28.6,
            "home": 1,
            "fg": 3.0,
            "fga": 14.0,
            "fg_pct": 0.214,
            "fg3": 1.0,
            "fg3a": 9.0,
            "fg3_pct": 0.111,
            "ft": 0.0,
            "fta": 0.0,
            "ft_pct": 0,
            "orb": 0.0,
            "drb": 1.0,
            "trb": 1.0,
            "ast": 1.0,
            "stl": 1.0,
            "blk": 0.0,
            "tov": 4.0,
            "pf": 1.0,
            "pts": 7.0,
            "plus_minus": 15.0,
            "ts_pct": 0.25,
            "efg_pct": 0.25,
            "fg3a_per_fga_pct": 0.643,
            "fta_per_fga_pct": 0.0,
            "orb_pct": 0.0,
            "drb_pct": 3.6,
            "trb_pct": 1.9,
            "ast_pct": 5.6,
            "stl_pct": 1.7,
            "blk_pct": 0.0,
            "tov_pct": 22.2,
            "usg_pct": 26.8,
            "off_rtg": 42.0,
            "def_rtg": 100.0,
            "bpm": -16.5
        },
        "templga01": {
            "mp": 18.52,
            "home": 1,
            "fg": 2.0,
            "fga": 5.0,
            "fg_pct": 0.4,
            "fg3": 1.0,
            "fg3a": 4.0,
            "fg3_pct": 0.25,
            "ft": 0.0,
            "fta": 0.0,
            "ft_pct": 0,
            "orb": 0.0,
            "drb": 2.0,
            "trb": 2.0,
            "ast": 2.0,
            "stl": 0.0,
            "blk": 0.0,
            "tov": 1.0,
            "pf": 1.0,
            "pts": 5.0,
            "plus_minus": 4.0,
            "ts_pct": 0.5,
            "efg_pct": 0.5,
            "fg3a_per_fga_pct": 0.8,
            "fta_per_fga_pct": 0.0,
            "orb_pct": 0.0,
            "drb_pct": 11.3,
            "trb_pct": 5.8,
            "ast_pct": 17.4,
            "stl_pct": 0.0,
            "blk_pct": 0.0,
            "tov_pct": 16.7,
            "usg_pct": 13.8,
            "off_rtg": 93.0,
            "def_rtg": 102.0,
            "bpm": -1.2
        },
        "alexani01": {
            "mp": 16.7,
            "home": 1,
            "fg": 3.0,
            "fga": 9.0,
            "fg_pct": 0.333,
            "fg3": 1.0,
            "fg3a": 4.0,
            "fg3_pct": 0.25,
            "ft": 0.0,
            "fta": 0.0,
            "ft_pct": 0,
            "orb": 0.0,
            "drb": 0.0,
            "trb": 0.0,
            "ast": 2.0,
            "stl": 0.0,
            "blk": 0.0,
            "tov": 1.0,
            "pf": 0.0,
            "pts": 7.0,
            "plus_minus": 3.0,
            "ts_pct": 0.389,
            "efg_pct": 0.389,
            "fg3a_per_fga_pct": 0.444,
            "fta_per_fga_pct": 0.0,
            "orb_pct": 0.0,
            "drb_pct": 0.0,
            "trb_pct": 0.0,
            "ast_pct": 21.8,
            "stl_pct": 0.0,
            "blk_pct": 0.0,
            "tov_pct": 10.0,
            "usg_pct": 25.5,
            "off_rtg": 79.0,
            "def_rtg": 104.0,
            "bpm": -5.2
        },
        "clarkga01": {
            "mp": 15.63,
            "home": 1,
            "fg": 3.0,
            "fga": 4.0,
            "fg_pct": 0.75,
            "fg3": 3.0,
            "fg3a": 4.0,
            "fg3_pct": 0.75,
            "ft": 1.0,
            "fta": 2.0,
            "ft_pct": 0.5,
            "orb": 0.0,
            "drb": 7.0,
            "trb": 7.0,
            "ast": 0.0,
            "stl": 0.0,
            "blk": 1.0,
            "tov": 1.0,
            "pf": 0.0,
            "pts": 10.0,
            "plus_minus": -1.0,
            "ts_pct": 1.025,
            "efg_pct": 1.125,
            "fg3a_per_fga_pct": 1.0,
            "fta_per_fga_pct": 0.5,
            "orb_pct": 0.0,
            "drb_pct": 46.7,
            "trb_pct": 24.1,
            "ast_pct": 0.0,
            "stl_pct": 0.0,
            "blk_pct": 5.7,
            "tov_pct": 17.0,
            "usg_pct": 16.0,
            "off_rtg": 140.0,
            "def_rtg": 90.0,
            "bpm": 16.9
        },
        "hayesja02": {
            "mp": 11.85,
            "home": 1,
            "fg": 2.0,
            "fga": 2.0,
            "fg_pct": 1.0,
            "fg3": 0.0,
            "fg3a": 0.0,
            "fg3_pct": 0,
            "ft": 1.0,
            "fta": 3.0,
            "ft_pct": 0.333,
            "orb": 1.0,
            "drb": 1.0,
            "trb": 2.0,
            "ast": 0.0,
            "stl": 0.0,
            "blk": 2.0,
            "tov": 1.0,
            "pf": 3.0,
            "pts": 5.0,
            "plus_minus": 4.0,
            "ts_pct": 0.753,
            "efg_pct": 1.0,
            "fg3a_per_fga_pct": 0.0,
            "fta_per_fga_pct": 1.5,
            "orb_pct": 9.4,
            "drb_pct": 8.8,
            "trb_pct": 9.1,
            "ast_pct": 0.0,
            "stl_pct": 0.0,
            "blk_pct": 15.0,
            "tov_pct": 23.1,
            "usg_pct": 15.5,
            "off_rtg": 110.0,
            "def_rtg": 91.0,
            "bpm": 0.9
        },
        "alvarjo01": {
            "mp": 10.78,
            "home": 1,
            "fg": 0.0,
            "fga": 4.0,
            "fg_pct": 0.0,
            "fg3": 0.0,
            "fg3a": 2.0,
            "fg3_pct": 0.0,
            "ft": 0.0,
            "fta": 0.0,
            "ft_pct": 0,
            "orb": 0.0,
            "drb": 1.0,
            "trb": 1.0,
            "ast": 1.0,
            "stl": 0.0,
            "blk": 0.0,
            "tov": 0.0,
            "pf": 2.0,
            "pts": 0.0,
            "plus_minus": -5.0,
            "ts_pct": 0.0,
            "efg_pct": 0.0,
            "fg3a_per_fga_pct": 0.5,
            "fta_per_fga_pct": 0.0,
            "orb_pct": 0.0,
            "drb_pct": 9.7,
            "trb_pct": 5.0,
            "ast_pct": 12.7,
            "stl_pct": 0.0,
            "blk_pct": 0.0,
            "tov_pct": 0.0,
            "usg_pct": 15.8,
            "off_rtg": 15.0,
            "def_rtg": 102.0,
            "bpm": -20.1
        }
    }
}